single_elimination/__init__.py
single_elimination/match.py
single_elimination/participant.py
single_elimination/tournament.py
single_elimination-1.2.0.dist-info/LICENSE
single_elimination-1.2.0.dist-info/METADATA
single_elimination-1.2.0.dist-info/WHEEL
single_elimination-1.2.0.dist-info/top_level.txt
single_elimination-1.2.0.dist-info/RECORD
