Metadata-Version: 2.1
Name: single-elimination
Version: 1.2.0
Summary: A single elimination tournament match handler.
Home-page: https://github.com/smwa/double_elimination
Author: Michael Smith
Author-email: michael.smith.ok@gmail.com
License: UNKNOWN
Platform: UNKNOWN
Classifier: Programming Language :: Python :: 3
Classifier: License :: OSI Approved :: MIT License
Classifier: Operating System :: OS Independent
Requires-Python: >=3.6
